speexdsp_ns/speexdsp_ns.py
speexdsp_ns/_speexdsp_ns.cpython-312-aarch64-linux-gnu.so
speexdsp_ns/speexdsp_ns_wrap.cpp
speexdsp_ns/noise_suppression.cpp
speexdsp_ns/__init__.py
speexdsp_ns/noise_suppression.h
speexdsp_ns/include/speex/speex_preprocess.h
speexdsp_ns/include/speex/speexdsp_types.h
speexdsp_ns/include/speex/speex_buffer.h
speexdsp_ns/include/speex/speex_echo.h
speexdsp_ns/include/speex/speex_resampler.h
speexdsp_ns/include/speex/speex_jitter.h
speexdsp_ns_vulcanlabs.libs/libspeexdsp-3d709243.so.1.5.2
speexdsp_ns_vulcanlabs-0.1.3.dist-info/WHEEL
speexdsp_ns_vulcanlabs-0.1.3.dist-info/top_level.txt
speexdsp_ns_vulcanlabs-0.1.3.dist-info/METADATA
speexdsp_ns_vulcanlabs-0.1.3.dist-info/RECORD
speexdsp_ns_vulcanlabs-0.1.3.dist-info/licenses/LICENSE
