Metadata-Version: 2.1
Name: speexdsp-ns-vulcanlabs
Version: 0.1.3
Summary: Python bindings of speexdsp noise suppression library (Vulcanlabs fork with multi-platform wheels)
Home-page: https://github.com/hiendang7613vulcan/speexdsp-ns-vulcanlabs
Author: Lucky Wong, Vulcanlabs
Author-email: Lucky Wong <luckyvictor1983@gmail.com>, Vulcanlabs <dev@vulcanlabs.co>
Maintainer-email: Vulcanlabs <dev@vulcanlabs.co>
License: BSD-3-Clause
Project-URL: Homepage, https://github.com/hiendang7613vulcan/speexdsp-ns-vulcanlabs
Project-URL: Repository, https://github.com/hiendang7613vulcan/speexdsp-ns-vulcanlabs
Project-URL: Original Source, https://github.com/TeaPoly/speexdsp-ns-python
Keywords: speexdsp,noise suppression,audio processing,speech enhancement
Platform: Linux
Platform: MacOS
Classifier: Development Status :: 4 - Beta
Classifier: License :: OSI Approved :: BSD License
Classifier: Operating System :: POSIX :: Linux
Classifier: Operating System :: MacOS
Classifier: Programming Language :: Python :: 3
Classifier: Programming Language :: Python :: 3.8
Classifier: Programming Language :: Python :: 3.9
Classifier: Programming Language :: Python :: 3.10
Classifier: Programming Language :: Python :: 3.11
Classifier: Programming Language :: Python :: 3.12
Classifier: Programming Language :: C++
Classifier: Topic :: Multimedia :: Sound/Audio :: Speech
Classifier: Topic :: Scientific/Engineering :: Artificial Intelligence
Requires-Python: >=3.8
License-File: LICENSE
